ghstack/github_schema.graphql
ghstack/circleci_real.py
ghstack/rage.py
ghstack/cherry_pick.py
ghstack/github_utils.py
ghstack/gpg_sign.py
ghstack/unlink.py
ghstack/types.py
ghstack/cli.py
ghstack/status.py
ghstack/logs.py
ghstack/forensics.py
ghstack/submit.py
ghstack/py.typed
ghstack/diff.py
ghstack/cache.py
ghstack/circleci.py
ghstack/checkout.py
ghstack/github_real.py
ghstack/__main__.py
ghstack/shell.py
ghstack/git.py
ghstack/github_fake.py
ghstack/config.py
ghstack/__init__.py
ghstack/action.py
ghstack/land.py
ghstack/trailers.py
ghstack/github.py
ghstack/test_prelude.py
ghstack-0.14.0.dist-info/licenses/LICENSE
ghstack-0.14.0.dist-info/WHEEL
ghstack-0.14.0.dist-info/entry_points.txt
ghstack-0.14.0.dist-info/METADATA
ghstack-0.14.0.dist-info/RECORD
