Metadata-Version: 2.4
Name: ghstack
Version: 0.14.0
Summary: Stack diff support for GitHub
Author: Edward Z. Yang
Author-email: Edward Z. Yang <ezyang@mit.edu>
License-Expression: MIT
License-File: LICENSE
Classifier: Programming Language :: Python :: 3
Classifier: License :: OSI Approved :: MIT License
Classifier: Operating System :: OS Independent
Requires-Dist: aiohttp>=3,<4
Requires-Dist: importlib-metadata>=1.4 ; python_full_version < '3.8'
Requires-Dist: requests>=2,<3
Requires-Dist: typing-extensions>=3
Requires-Dist: click>=8,<9
Requires-Dist: flake8>=7.0.0,<8.0.0
Requires-Python: >=3.9.1, <4.0.0
Project-URL: repository, https://github.com/ezyang/ghstack
